nordvpn_exporter/__init__.py
nordvpn_exporter/exporter.py
nordvpn_exporter-1.1.dist-info/LICENSE
nordvpn_exporter-1.1.dist-info/METADATA
nordvpn_exporter-1.1.dist-info/WHEEL
nordvpn_exporter-1.1.dist-info/entry_points.txt
nordvpn_exporter-1.1.dist-info/top_level.txt
nordvpn_exporter-1.1.dist-info/RECORD
