Metadata-Version: 2.1
Name: nordvpn-exporter
Version: 1.1
Summary: A simple NordVPN Exporter
Home-page: https://github.com/veerendra2/nordvpn-exporter
Author: Veerendra K
License: Apache 2.0
Project-URL: Documentation, https://github.com/veerendra2/nordvpn-exporter/blob/main/README.md
Project-URL: Bug Tracker, https://github.com/veerendra2/nordvpn-exporter/issues
Project-URL: Source Code, https://github.com/veerendra2/nordvpn-exporter
Platform: UNKNOWN
Classifier: Programming Language :: Python :: 3.4
Classifier: License :: OSI Approved :: Apache Software License
Classifier: Development Status :: 4 - Beta
Requires-Python: >=3.4
License-File: LICENSE
Requires-Dist: prometheus-client
Requires-Dist: waitress
Requires-Dist: Flask
